berlin_gelaendemodelle_downloader/__init__.py
berlin_gelaendemodelle_downloader/cli.py
berlin_gelaendemodelle_downloader/constant.py
berlin_gelaendemodelle_downloader/download.py
berlin_gelaendemodelle_downloader/file.py
berlin_gelaendemodelle_downloader/utils.py
berlin_opendata_downloader-1.5.2.dist-info/AUTHORS.rst
berlin_opendata_downloader-1.5.2.dist-info/LICENSE.txt
berlin_opendata_downloader-1.5.2.dist-info/METADATA
berlin_opendata_downloader-1.5.2.dist-info/WHEEL
berlin_opendata_downloader-1.5.2.dist-info/entry_points.txt
berlin_opendata_downloader-1.5.2.dist-info/top_level.txt
berlin_opendata_downloader-1.5.2.dist-info/RECORD
