Metadata-Version: 2.1
Name: berlin-opendata-downloader
Version: 1.5.2
Summary: Client to download height information of Berlin from OpenData sources. Can compress on the fly.
Home-page: https://github.com/se-jaeger/berlin-gelaendemodelle-downloader
Author: Sebastian Jaeger
Author-email: message@sebastian-jaeger.me
License: apache
Project-URL: Documentation, https://berlin-gelaendemodelle-downloader.readthedocs.io/en/latest/
Platform: any
Classifier: Development Status :: 4 - Beta
Classifier: Programming Language :: Python
Requires-Python: >=3.6
Requires-Dist: Click
Requires-Dist: beautifulsoup4
Requires-Dist: pandas
Requires-Dist: tqdm
Requires-Dist: requests
Requires-Dist: geopandas
Provides-Extra: testing
Requires-Dist: pytest ; extra == 'testing'
Requires-Dist: pytest-cov ; extra == 'testing'
